my_code_display/__init__.py
my_code_display/main.py
my_code_display-3.0.0.dist-info/METADATA
my_code_display-3.0.0.dist-info/WHEEL
my_code_display-3.0.0.dist-info/entry_points.txt
my_code_display-3.0.0.dist-info/top_level.txt
my_code_display-3.0.0.dist-info/RECORD
